tqdme/__init__.py
tqdme/server.py
tqdme/tqdme.py
tqdme/utils.py
tqdme-0.0.3.dist-info/METADATA
tqdme-0.0.3.dist-info/WHEEL
tqdme-0.0.3.dist-info/RECORD
