Metadata-Version: 2.3
Name: tqdme
Version: 0.0.3
Summary: Forward progress from tqdm to a public website
Project-URL: Homepage, https://github.com/tqdme/tqdme
Project-URL: Bug Tracker, https://github.com/tqdme/tqdme/issues
Author-email: Garrett Flynn <garrettmflynn@gmail.com>
License: BSD 3-Clause License
Keywords: bar,meter,progress,progressbar,progressmeter,time,tqdm
Classifier: Intended Audience :: Developers
Classifier: License :: OSI Approved :: BSD License
Classifier: Operating System :: MacOS
Classifier: Operating System :: Microsoft :: Windows
Classifier: Operating System :: Unix
Classifier: Programming Language :: Python
Classifier: Programming Language :: Python :: 3.8
Classifier: Programming Language :: Python :: 3.9
Classifier: Programming Language :: Python :: 3.10
Classifier: Programming Language :: Python :: 3.11
Requires-Python: >=3.9
Requires-Dist: requests
Requires-Dist: tqdm>=4.49.0
Provides-Extra: server
Requires-Dist: flask; extra == 'server'
Requires-Dist: flask-cors; extra == 'server'
Requires-Dist: flask-socketio; extra == 'server'
Provides-Extra: test
Requires-Dist: pytest; extra == 'test'
Requires-Dist: pytest-asyncio; extra == 'test'
Requires-Dist: pytest-cov; extra == 'test'
